volue_insight_timeseries/VERSION
volue_insight_timeseries/__init__.py
volue_insight_timeseries/auth.py
volue_insight_timeseries/curves.py
volue_insight_timeseries/events.py
volue_insight_timeseries/session.py
volue_insight_timeseries/util.py
volue_insight_timeseries-2.1.0.dist-info/licenses/LICENSE
volue_insight_timeseries-2.1.0.dist-info/METADATA
volue_insight_timeseries-2.1.0.dist-info/WHEEL
volue_insight_timeseries-2.1.0.dist-info/top_level.txt
volue_insight_timeseries-2.1.0.dist-info/RECORD
